{"title": "Here are 250 Ivy League courses you can take online right now for\u00a0free", "name": "2445", "content": "Here are 250 Ivy League courses you can take online right now for\u00a0free The 8 Ivy League schools are among the most prestigious colleges in the world. They include Brown, Harvard, Cornell, Princeton, Dartmouth, Yale, and Columbia universities, and the University of Pennsylvania. All eight schools place in the top fifteen of the U.S. News and World Report 2017 national university rankings. These Ivy League schools are also highly selective and extremely hard to get into. But the good news is that all these universities now offer free online courses across multiple online course platforms. So far, they\u2019ve created over 300 courses, of which around 250 are still active. Class Central has made a collection of all these, which you can explore below. I\u2019ve split these courses into the following categories: I\u2019ve also assembled these courses on Class Central\u2019s collection page for Ivy League MOOCs. This collection gets updated automatically as new courses are added. You can subscribe to receive updates by clicking the blue \u201cfollow\u201d button there. Ivy League MOOCs collection on Class\u00a0Central You can also watch Quincy Larson\u2019s interview with me about this article. Computer Science (28\u00a0courses) Introduction to Computer ScienceHarvard University via edX\u2605\u2605\u2605\u2605\u2605 (52 ratings) Algorithms, Part IPrinceton University via Coursera\u2605\u2605\u2605\u2605\u2606 (48 ratings) Machine LearningGeorgia Institute of Technology via Udacity\u2605\u2605\u2605\u2605\u2605 (4 ratings) Analysis of AlgorithmsPrinceton University via Coursera\u2605\u2605\u2605\u2605\u2605 (4 ratings) Bitcoin and Cryptocurrency TechnologiesPrinceton University via Coursera\u2605\u2605\u2605\u2605\u2606 (10 ratings) Introduction to Spreadsheets and ModelsUniversity of Pennsylvania via Coursera\u2605\u2605\u2605\u2605\u2605 (3 ratings) Computer ArchitecturePrinceton University via Coursera\u2605\u2605\u2605\u2605\u2605 (4 ratings) Machine LearningBrown University via Udacity\u2605\u2605\u2605\u2605\u2605 (1 rating) Networks Illustrated: Principles without CalculusPrinceton University via Coursera\u2605\u2605\u2605\u2605\u2606 (3 ratings) Software Defined NetworkingPrinceton University via Coursera\u2605\u2605\u2605\u2605\u2606 (5 ratings) Machine Learning 1\u200a\u2014\u200aSupervised LearningBrown University via Udacity\u2605\u2605\u2605\u2605\u2606 (1 rating) Machine Learning: Unsupervised LearningBrown University via Udacity\u2605\u2605\u2605\u2605\u2606 (1 rating) Introduction to Bioconductor: Annotation and Analysis of Genomes and Genomic AssaysHarvard University via edX\u2605\u2605\u2605\u2605\u2606 (1 rating) Statistics and RHarvard University via edX\u2605\u2605\u2605\u2605\u2606 (13 ratings) Networks: Friends, Money, and BytesPrinceton University via Coursera\u2605\u2605\u2605\u2606\u2606 (1 rating) The Computing Technology Inside Your SmartphoneCornell University via edX\u2605\u2605\u2605\u2605\u2605 (2 ratings) Using Python for ResearchHarvard University via edX Case Studies in Functional GenomicsHarvard University via edX\u2605\u2605\u2605\u2606\u2606 (1 rating) Machine Learning for Data Science and AnalyticsColumbia University via edX\u2605\u2605\u2605\u2606\u2606 (15 ratings) Reinforcement LearningBrown University via Udacity\u2605\u2605\u2606\u2606\u2606 (6 ratings) Enabling Technologies for Data Science and Analytics: The Internet of ThingsColumbia University via edX\u2605\u2606\u2606\u2606\u2606 (5 ratings) Statistical Thinking for Data Science and AnalyticsColumbia University via edX\u2605\u2605\u2606\u2606\u2606 (13 ratings) Artificial Intelligence (AI)Columbia University via edX\u2605\u2606\u2606\u2606\u2606 (1 rating) Machine LearningColumbia University via edX Big Data in EducationColumbia University via edX High-performance Computing for Reproducible GenomicsHarvard University via edX AP\u00ae Computer Science PrinciplesHarvard University via edX Animation and CGI MotionColumbia University via edX Humanities (44\u00a0courses) Modern & Contemporary American Poetry (\u201cModPo\u201d)University of Pennsylvania via Coursera\u2605\u2605\u2605\u2605\u2605 (128 ratings) Moralities of Everyday LifeYale University via Coursera\u2605\u2605\u2605\u2605\u2605 (31 ratings) The Civil War and Reconstruction\u200a\u2014\u200a1865\u20131890: The Unfinished RevolutionColumbia University via edX\u2605\u2605\u2605\u2605\u2605 (5 ratings) Ancient Philosophy: Plato & His PredecessorsUniversity of Pennsylvania via Coursera\u2605\u2605\u2605\u2605\u2605 (9 ratings) The Civil War and Reconstruction\u200a\u2014\u200a1861\u20131865: A New Birth of FreedomColumbia University via edX\u2605\u2605\u2605\u2605\u2605 (4 ratings) The Civil War and Reconstruction\u200a\u2014\u200a1850\u20131861: A Nation DividedColumbia University via edX\u2605\u2605\u2605\u2605\u2605 (5 ratings) American Capitalism: A HistoryCornell University via edX\u2605\u2605\u2605\u2605\u2605 (3 ratings) Visualizing Japan (1850s-1930s): Westernization, Protest, ModernityHarvard University via edX\u2605\u2605\u2605\u2605\u2605 (5 ratings) Greek and Roman MythologyUniversity of Pennsylvania via Coursera\u2605\u2605\u2605\u2605\u2606 (11 ratings) Introduction to Ancient Egypt and Its CivilizationUniversity of Pennsylvania via Coursera\u2605\u2605\u2605\u2605\u2605 (1 rating) The Book: Books in the Medieval LiturgyHarvard University via edX\u2605\u2605\u2605\u2605\u2605 (1 rating) Buddhism Through Its ScripturesHarvard University via edX\u2605\u2605\u2605\u2605\u2605 (1 rating) PredictionX: John Snow and the Cholera Epidemic of 1854Harvard University via edX\u2605\u2605\u2605\u2605\u2605 (1 rating) Effective AltruismPrinceton University via Coursera\u2605\u2605\u2605\u2605\u2605 (2 ratings) The Ethics of EatingCornell University via edX\u2605\u2605\u2605\u2605\u2605 (2 ratings) Religious Literacy: Traditions and ScripturesHarvard University via edX\u2605\u2605\u2605\u2605\u2606 (3 ratings) Journey of the Universe: The Unfolding of LifeYale University via Coursera\u2605\u2605\u2605\u2605\u2606 (1 rating) Ancient Philosophy: Aristotle and His SuccessorsUniversity of Pennsylvania via Coursera\u2605\u2605\u2605\u2605\u2606 (7 ratings) Christianity Through Its ScripturesHarvard University via edX\u2605\u2605\u2605\u2605\u2606 (2 ratings) Masterpieces of World LiteratureHarvard University via edX\u2605\u2605\u2605\u2606\u2606 (1 rating) The Book: The Medieval Book of Hours: Art and Devotion in the Later Middle AgesHarvard University via edX\u2605\u2605\u2605\u2606\u2606 (2 ratings) The Ancient Greek Hero in 24 HoursHarvard University via edX\u2605\u2605\u2605\u2606\u2606 (2 ratings) China (Part 1): Political and Intellectual Foundations: From the Sage Kings to Confucius and the LegalistsHarvard University via edX\u2605\u2605\u2605\u2605\u2605 (7 ratings) China (Part 2): The Creation and End of Centralized EmpireHarvard University via edX\u2605\u2605\u2605\u2605\u2605 (6 ratings) China (Part 3): Cosmopolitan Tang: Aristocratic CultureHarvard University via edX\u2605\u2605\u2605\u2605\u2605 (4 ratings) China (Part 4): Literati China: Examinations and Neo-ConfucianismHarvard University via edX\u2605\u2605\u2605\u2605\u2605 (6 ratings) China (Part 5): From a Global Empire under the Mongols to a Global Economy under the Ming DynastyHarvard University via edX\u2605\u2605\u2605\u2605\u2605 (4 ratings) China (Part 6): The Manchus and the Qing DynastyHarvard University via edX\u2605\u2605\u2605\u2605\u2605 (6 ratings) China (Part 7): Invasions, Rebellions and the Fall of Imperial ChinaHarvard University via edX\u2605\u2605\u2605\u2605\u2605 (4 ratings) China (Part 8): Creating Modern China: The Birth of a NationHarvard University via edX\u2605\u2605\u2605\u2605\u2605 (5 ratings) China (Part 9): China and CommunismHarvard University via edX\u2605\u2605\u2605\u2605\u2605 (4 ratings) China (Part 10): Greater China Today: The People\u2019s Republic, Taiwan, and Hong KongHarvard University via edX\u2605\u2605\u2605\u2605\u2605 (4 ratings) English for JournalismUniversity of Pennsylvania via Coursera English for Career DevelopmentUniversity of Pennsylvania via Coursera The Worldview of Thomas Berry: The Flourishing of the Earth CommunityYale University via Coursera Question Reality! Science, philosophy, and the search for meaningDartmouth via edX The Book: Book Sleuthing: What 19th-Century Books Can Tell Us About the Rise of the Reading Public?Harvard University via edX Writing Case Studies: Science of DeliveryPrinceton University via edX The American Renaissance: Classic Literature of the 19th CenturyDartmouth via edX Islam Through Its ScripturesHarvard University via edX Hinduism Through Its ScripturesHarvard University via edX Judaism Through Its ScripturesHarvard University via edX Hamlet\u2019s GhostHarvard University via edX English for Business and EntrepreneurshipUniversity of Pennsylvania via Coursera Social Sciences (37\u00a0courses) JusticeHarvard University via edX\u2605\u2605\u2605\u2605\u2605 (27 ratings) An Introduction to American LawUniversity of Pennsylvania via Coursera\u2605\u2605\u2605\u2605\u2605 (13 ratings) Introduction to Key Constitutional Concepts and Supreme Court CasesUniversity of Pennsylvania via Coursera\u2605\u2605\u2605\u2605\u2605 (5 ratings) The Book: Making and Meaning in the Medieval ManuscriptHarvard University via edX\u2605\u2605\u2605\u2605\u2605 (3 ratings) America\u2019s Unwritten ConstitutionYale University via Coursera\u2605\u2605\u2605\u2605\u2605 (3 ratings) Buddhism and Modern Psychology Princeton University via Coursera\u2605\u2605\u2605\u2605\u2606 (19 ratings) Tangible Things: Discovering History Through Artworks, Artifacts, Scientific Specimens, and the Stuff Around YouHarvard University via edX\u2605\u2605\u2605\u2605\u2605 (5 ratings) Moral Foundations of Politics Yale University via Coursera\u2605\u2605\u2605\u2605\u2606 (11 ratings) The Book: Monasteries, Schools, and Notaries, Part 2: Introduction to the Transitional Gothic ScriptHarvard University via edX\u2605\u2605\u2605\u2605\u2605 (2 ratings) Contract Law: From Trust to Promise to ContractHarvard University via edX\u2605\u2605\u2605\u2605\u2606 (7 ratings) Microeconomics: When Markets FailUniversity of Pennsylvania via Coursera\u2605\u2605\u2605\u2605\u2605 (1 rating) The Book: Print and Manuscript in Western Europe, Asia and the Middle East (1450\u20131650)Harvard University via edX\u2605\u2605\u2605\u2605\u2605 (1 rating) The Book: The History of the Book in the 17th and 18th Century EuropeHarvard University via edX\u2605\u2605\u2605\u2605\u2605 (1 rating) The Book: Scrolls in the Age of the BookHarvard University via edX\u2605\u2605\u2605\u2605\u2605 (1 rating) Intellectual Property Law and Policy\u200a\u2014\u200aPart 1: IP and Patent LawsUniversity of Pennsylvania via edX\u2605\u2605\u2605\u2605\u2605 (1 rating) The History of Medieval Medicine Through Jewish ManuscriptsUniversity of Pennsylvania via edX\u2605\u2605\u2605\u2605\u2605 (1 rating) JuryX: Deliberations for Social ChangeHarvard University via edX\u2605\u2605\u2605\u2605\u2605 (2 ratings) Revolutionary Ideas: Utility, Justice, Equality, FreedomUniversity of Pennsylvania via Coursera\u2605\u2605\u2605\u2605\u2606 (3 ratings) American GovernmentHarvard University via edX\u2605\u2605\u2605\u2605\u2606 (3 ratings) Paradoxes of WarPrinceton University via Coursera\u2605\u2605\u2605\u2605\u2606 (9 ratings) America\u2019s Written ConstitutionYale University via Coursera\u2605\u2605\u2605\u2605\u2606 (8 ratings) A Law Student\u2019s ToolkitYale University via Coursera\u2605\u2605\u2605\u2605\u2606 (1 rating) The Book: Monasteries, Schools, and Notaries, Part 1: Reading the Late Medieval Marseille ArchiveHarvard University via edX\u2605\u2605\u2605\u2605\u2606 (3 ratings) Intellectual Property Law and Policy\u200a\u2014\u200aPart 2: Copyright and Trademark LawsUniversity of Pennsylvania via edX\u2605\u2605\u2605\u2605\u2606 (1 rating) Bioethics: The Law, Medicine, and Ethics of Reproductive Technologies and GeneticsHarvard University via edX\u2605\u2605\u2605\u2605\u2606 (2 ratings) Microeconomics: The Power of MarketsUniversity of Pennsylvania via Coursera\u2605\u2605\u2605\u2605\u2606 (5 ratings) Introduction to SociologyPrinceton University via Coursera\u2605\u2605\u2605\u2605\u2606 (4 ratings) Wiretaps to Big Data: Privacy and Surveillance in the Age of InterconnectionCornell University via edX\u2605\u2605\u2605\u2606\u2606 (1 rating) Central Challenges of American National Security, Strategy, and the PressHarvard University via edX\u2605\u2605\u2605\u2606\u2606 (1 rating) Networks, Crowds and MarketsCornell University via edX\u2605\u2605\u2606\u2606\u2606 (1 rating) Top 10 Social Issues for the President\u2019s First 100 DaysUniversity of Pennsylvania via edX CorruptionUniversity of Pennsylvania via Coursera Revolutionary Ideas: Borders, Elections, Constitutions, PrisonsUniversity of Pennsylvania via Coursera Social Norms, Social Change IUniversity of Pennsylvania via Coursera Social Norms, Social Change IIUniversity of Pennsylvania via Coursera Making Government Work in Hard PlacesPrinceton University via edX Freedom of Expression in the Age of GlobalizationColumbia University via edX Art & Design (16\u00a0courses) Introduction to Classical MusicYale University via Coursera\u2605\u2605\u2605\u2605\u2605 (14 ratings) GamificationUniversity of Pennsylvania via Coursera\u2605\u2605\u2605\u2605\u2606 (52 ratings) Design: Creation of Artifacts in SocietyUniversity of Pennsylvania via Coursera\u2605\u2605\u2605\u2605\u2605 (13 ratings) First Nights: Handel\u2019s Messiah and Baroque OratorioHarvard University via edX\u2605\u2605\u2605\u2605\u2605 (1 rating) First Nights: Beethoven\u2019s 9th Symphony and the 19th Century OrchestraHarvard University via edX\u2605\u2605\u2605\u2605\u2605 (1 rating) First Nights: Monteverdi\u2019s L\u2019Orfeo and the Birth of OperaHarvard University via edX\u2605\u2605\u2605\u2605\u2605 (1 rating) First Nights: Berlioz\u2019s Symphonie Fantastique and Program Music in the 19th CenturyHarvard University via edX\u2605\u2605\u2605\u2605\u2605 (1 rating) Hollywood: History, Industry, ArtUniversity of Pennsylvania via edX\u2605\u2605\u2605\u2605\u2605 (1 rating) First Nights: Igor Stravinsky\u2019s The Rite of Spring: Modernism, Ballet, and RiotsHarvard University via edX\u2605\u2605\u2605\u2605\u2606 (1 rating) Music and Social ActionYale University via Coursera\u2605\u2605\u2605\u2605\u2606 (1 rating) Listening to World MusicUniversity of Pennsylvania via Coursera\u2605\u2605\u2605\u2605\u2606 (3 ratings) Introduction to Italian OperaDartmouth via edX\u2605\u2605\u2605\u2606\u2606 (2 ratings) The Architectural ImaginationHarvard University via edX The History of Music Production TechniquesColumbia University via Kadenze Introduction to German OperaDartmouth via edX Reinventing the PianoPrinceton University via Kadenze Science (19\u00a0courses) The Age of Sustainable DevelopmentColumbia University via Coursera\u2605\u2605\u2605\u2605\u2605 (11 ratings) Science & Cooking: From Haute Cuisine to Soft Matter Science (part 1)Harvard University via edX\u2605\u2605\u2605\u2605\u2605 (7 ratings) Principles of BiochemistryHarvard University via edX\u2605\u2605\u2605\u2605\u2605 (3 ratings) Fundamentals of Neuroscience Part 2: Neurons and NetworksHarvard University via edX\u2605\u2605\u2605\u2605\u2605 (3 ratings) Introduction to Sustainable DevelopmentColumbia University via Coursera\u2605\u2605\u2605\u2605\u2605 (7 ratings) Super-Earths And LifeHarvard University via edX\u2605\u2605\u2605\u2605\u2605 (4 ratings) Fundamentals of Neuroscience Part 1: Electrical Properties of the NeuronHarvard University via edX\u2605\u2605\u2605\u2605\u2606 (7 ratings) Sharks! Global Biodiversity, Biology, and ConservationCornell University via edX\u2605\u2605\u2605\u2605\u2605 (1 rating) The Fundamentals of Neuroscience Part 3: The BrainHarvard University via edX\u2605\u2605\u2605\u2605\u2605 (1 rating) AnatomyX: Musculoskeletal CasesHarvard University via edX\u2605\u2605\u2605\u2605\u2605 (2 ratings) Introduction to Environmental ScienceDartmouth via edX\u2605\u2605\u2605\u2605\u2606 (5 ratings) Imagining Other EarthsPrinceton University via Coursera\u2605\u2605\u2605\u2605\u2606 (1 rating) High-Dimensional Data AnalysisHarvard University via edX\u2605\u2605\u2605\u2605\u2606 (3 ratings) Relativity and AstrophysicsCornell University via edX\u2605\u2605\u2605\u2605\u2606 (5 ratings) The Einstein RevolutionHarvard University via edX\u2605\u2605\u2606\u2606\u2606 (1 rating) Cell Biology: MitochondriaHarvard University via edX\u2605\u2605\u2606\u2606\u2606 (1 rating) Basic Behavioral NeurologyUniversity of Pennsylvania via Coursera\u2605\u2605\u2606\u2606\u2606 (4 ratings) Journey Conversations: Weaving Knowledge and ActionYale University via Coursera Sustainability, Resilience, and SocietyHarvard University via edX Health & Medicine(19 subjects) Vital Signs: Understanding What the Body Is Telling UsUniversity of Pennsylvania via Coursera\u2605\u2605\u2605\u2605\u2605 (34 ratings) Introduction to Breast CancerYale University via Coursera\u2605\u2605\u2605\u2605\u2605 (2 ratings) Readings in Global HealthHarvard University via edX\u2605\u2605\u2605\u2605\u2605 (1 rating) Health and SocietyHarvard University via edX\u2605\u2605\u2605\u2605\u2605 (1 rating) Global Health Case Studies from a Biosocial PerspectiveHarvard University via edX\u2605\u2605\u2605\u2605\u2605 (1 rating) Improving Global Health: Focusing on Quality and SafetyHarvard University via edX\u2605\u2605\u2605\u2605\u2606 (3 ratings) Introduction to Dental MedicineUniversity of Pennsylvania via Coursera\u2605\u2605\u2605\u2605\u2606 (4 ratings) Fundamentals of PharmacologyUniversity of Pennsylvania via Coursera\u2605\u2605\u2605\u2605\u2606 (6 ratings) United States Health PolicyHarvard University via edX\u2605\u2605\u2605\u2605\u2605 (2 ratings) Going Out on a Limb: Anatomy of the Upper LimbUniversity of Pennsylvania via edX\u2605\u2605\u2605\u2605\u2606 (2 ratings) Humanitarian Response to Conflict and DisasterHarvard University via edX\u2605\u2605\u2605\u2605\u2606 (1 rating) PH556X: Practical Improvement Science in Health Care: A Roadmap for Getting ResultsHarvard University via edX HI-FIVE: Health Informatics For Innovation, Value & Enrichment (Clinical Perspective)Columbia University via Coursera Fundamentals of Clinical TrialsHarvard University via edX Innovating in Health CareHarvard University via edX Lessons from Ebola: Preventing the Next PandemicHarvard University via edX The Opioid Crisis in AmericaHarvard University via edX The Science and Politics of the GMOCornell University via edX Essentials of Global HealthYale University via Coursera Business & Management (46\u00a0courses) Introduction to Financial AccountingUniversity of Pennsylvania via Coursera\u2605\u2605\u2605\u2605\u2605 (38 ratings) Introduction to MarketingUniversity of Pennsylvania via Coursera\u2605\u2605\u2605\u2605\u2606 (47 ratings) Introduction to Corporate FinanceWharton School of the University of Pennsylvania via Coursera\u2605\u2605\u2605\u2605\u2606 (16 ratings) A Preview Course on The 5 Killer Risks of Enterprise Risk ManagementColumbia University via Canvas Network\u2605\u2605\u2605\u2605\u2605 (3 ratings) Introduction to Negotiation: A Strategic Playbook for Becoming a Principled and Persuasive NegotiatorYale University via Coursera\u2605\u2605\u2605\u2605\u2605 (2 ratings) The Global Financial CrisisYale University via Coursera\u2605\u2605\u2605\u2605\u2606 (9 ratings) Arts and Culture StrategyUniversity of Pennsylvania via Coursera\u2605\u2605\u2605\u2605\u2605 (2 ratings) Operations AnalyticsUniversity of Pennsylvania via Coursera\u2605\u2605\u2605\u2605\u2605 (4 ratings) Financial MarketsYale University via Coursera\u2605\u2605\u2605\u2605\u2606 (21 ratings) Introducci\u00f3n al MarketingUniversity of Pennsylvania via Coursera\u2605\u2605\u2605\u2605\u2605 (1 rating) Financial Engineering and Risk Management Part IColumbia University via Coursera\u2605\u2605\u2605\u2605\u2606 (10 ratings) Introduction to Operations ManagementWharton School of the University of Pennsylvania via Coursera\u2605\u2605\u2605\u2605\u2606 (29 ratings) Entrepreneurship 4: Financing and ProfitabilityUniversity of Pennsylvania via Coursera\u2605\u2605\u2605\u2605\u2606 (3 ratings) Financial Engineering and Risk Management Part IIColumbia University via Coursera\u2605\u2605\u2605\u2605\u2606 (3 ratings) Entrepreneurship 2: Launching your Start-UpUniversity of Pennsylvania via Coursera\u2605\u2605\u2605\u2605\u2606 (4 ratings) More Introduction to Financial AccountingUniversity of Pennsylvania via Coursera\u2605\u2605\u2605\u2605\u2606 (4 ratings) Entrepreneurship 1: Developing the OpportunityUniversity of Pennsylvania via Coursera\u2605\u2605\u2605\u2605\u2606 (4 ratings) Global Human Capital TrendsColumbia University via Canvas Network\u2605\u2605\u2605\u2605\u2606 (5 ratings) People AnalyticsUniversity of Pennsylvania via Coursera\u2605\u2605\u2605\u2605\u2606 (4 ratings) Social Impact Strategy: Tools for Entrepreneurs and InnovatorsUniversity of Pennsylvania via Coursera\u2605\u2605\u2605\u2605\u2606 (4 ratings) Introduction to Global Hospitality ManagementCornell University via edX\u2605\u2605\u2605\u2605\u2606 (2 ratings) Fundamentals of Quantitative ModelingUniversity of Pennsylvania via Coursera\u2605\u2605\u2605\u2605\u2606 (2 ratings) Accounting AnalyticsUniversity of Pennsylvania via Coursera\u2605\u2605\u2605\u2605\u2606 (5 ratings) Viral Marketing and How to Craft Contagious ContentUniversity of Pennsylvania via Coursera\u2605\u2605\u2605\u2605\u2606 (5 ratings) Construction SchedulingColumbia University via Coursera\u2605\u2606\u2606\u2606\u2606 (1 rating) Customer AnalyticsUniversity of Pennsylvania via Coursera\u2605\u2605\u2605\u2606\u2606 (14 ratings) Construction FinanceColumbia University via Coursera Building High-Performing TeamsUniversity of Pennsylvania via Coursera Managing Social and Human CapitalUniversity of Pennsylvania via Coursera Decision-Making and ScenariosUniversity of Pennsylvania via Coursera Construction Project ManagementColumbia University via Coursera Entrepreneurship and Healthcare in Emerging EconomiesHarvard University via edX Digital Marketing, Social Media and E-Commerce for Your BusinessUniversity of Pennsylvania via edX Entrepreneurship in Emerging EconomiesHarvard University via edX The Power of Team CultureUniversity of Pennsylvania via Coursera Optimizing Diversity on TeamsUniversity of Pennsylvania via Coursera Creating a Team Culture of Continuous LearningUniversity of Pennsylvania via Coursera \u4f01\u4e1a\u91d1\u878d\u6982\u8bba\uff08\u4e2d\u6587\u7248\uff09University of Pennsylvania via Coursera \u5e02\u573a\u8425\u9500\u6982\u8bba (\u4e2d\u6587\u7248\uff09University of Pennsylvania via Coursera Introducci\u00f3n a la Contabilidad FinancieraUniversity of Pennsylvania via Coursera \u8fd0\u8425\u7ba1\u7406\u6982\u8bba\uff08\u4e2d\u6587\u7248\uff09University of Pennsylvania via Coursera Introducci\u00f3n a la Gesti\u00f3n de OperacionesUniversity of Pennsylvania via Coursera Modeling Risk and RealitiesUniversity of Pennsylvania via Coursera \u8d22\u52a1\u4f1a\u8ba1\u6982\u8bba\uff08\u4e2d\u6587\u7248\uff09University of Pennsylvania via Coursera Introducci\u00f3n a las Finanzas CorporativasUniversity of Pennsylvania via Coursera Construction Cost Estimating and Cost ControlColumbia University via Coursera Innovate on DemandColumbia University via Coursera A Preview Course on Collaborative Knowledge ServicesColumbia University via Canvas Network\u2605\u2605\u2605\u2605\u2605 (2 ratings) SuccessUniversity of Pennsylvania via Coursera Mathematics (8\u00a0courses) Calculus: Single Variable Part 1\u200a\u2014\u200aFunctionsUniversity of Pennsylvania via Coursera\u2605\u2605\u2605\u2605\u2605 (5 ratings) Calculus: Single Variable Part 2\u200a\u2014\u200aDifferentiationUniversity of Pennsylvania via Coursera\u2605\u2605\u2605\u2605\u2605 (4 ratings) Introduction to Linear Models and Matrix AlgebraHarvard University via edX\u2605\u2605\u2605\u2605\u2605 (8 ratings) Calculus: Single Variable Part 4\u200a\u2014\u200aApplicationsUniversity of Pennsylvania via Coursera\u2605\u2605\u2605\u2605\u2605 (3 ratings) Statistical Inference and Modeling for High-throughput ExperimentsHarvard University via edX\u2605\u2605\u2605\u2605\u2605 (3 ratings) Calculus: Single Variable Part 3\u200a\u2014\u200aIntegrationUniversity of Pennsylvania via Coursera\u2605\u2605\u2605\u2605\u2606 (4 ratings) Analytic CombinatoricsPrinceton University via Coursera\u2605\u2605\u2605\u2605\u2606 (2 ratings) Single Variable CalculusUniversity of Pennsylvania via Coursera Education & Teaching (14\u00a0courses) American Education Reform: History, Policy, PracticeUniversity of Pennsylvania via Coursera\u2605\u2605\u2605\u2605\u2605 (8 ratings) Leaders of LearningHarvard University via edX\u2605\u2605\u2605\u2605\u2606 (12 ratings) Saving Schools, Mini-Course 1: History and Politics of U.S. EducationHarvard University via edX\u2605\u2605\u2605\u2605\u2606 (3 ratings) Saving Schools, Mini-Course 2: Teacher PoliciesHarvard University via edX\u2605\u2605\u2605\u2605\u2606 (1 rating) Saving Schools, Mini-Course 3: Accountability and National StandardsHarvard University via edX\u2605\u2605\u2605\u2605\u2606 (1 rating) Saving Schools, Mini-Course 4: School ChoiceHarvard University via edX\u2605\u2605\u2605\u2605\u2606 (1 rating) Applying to U.S. UniversitiesUniversity of Pennsylvania via Coursera\u2605\u2605\u2605\u2605\u2606 (10 ratings) How to Apply to CollegeUniversity of Pennsylvania via Coursera Introduction to Data Wise: A Collaborative Process to Improve Learning & TeachingHarvard University via edX Introduction to Family Engagement in EducationHarvard University via edX Understanding Classroom InteractionUniversity of Pennsylvania via edX The Science of Learning\u200a\u2014\u200aWhat Every Teacher Should KnowColumbia University via edX English for Science, Technology, Engineering, and MathematicsUniversity of Pennsylvania via Coursera Orchestrating Whole Classroom DiscussionUniversity of Pennsylvania via Coursera Engineering (13\u00a0courses) The Engineering of Structures Around UsDartmouth via edX\u2605\u2605\u2605\u2605\u2605 (2 ratings) A Hands-on Introduction to Engineering SimulationsCornell University via edX\u2605\u2605\u2605\u2605\u2605 (2 ratings) The Art of Structural Engineering: BridgesPrinceton University via edX\u2605\u2605\u2605\u2605\u2605 (3 ratings) Designing CitiesUniversity of Pennsylvania via Coursera\u2605\u2605\u2605\u2605\u2606 (6 ratings) MOS TransistorsColumbia University via Coursera\u2605\u2605\u2605\u2605\u2605 (1 rating) Energy Within Environmental ConstraintsHarvard University via edX\u2605\u2605\u2605\u2605\u2605 (1 rating) Robotics: Aerial RoboticsUniversity of Pennsylvania via Coursera\u2605\u2605\u2605\u2605\u2606 (5 ratings) Reclaiming Broken Places: Introduction to Civic EcologyCornell University via edX\u2605\u2605\u2605\u2606\u2606 (1 rating) Robotics: Computational Motion PlanningUniversity of Pennsylvania via Coursera\u2605\u2605\u2606\u2606\u2606 (1 rating) Robotics: Estimation and LearningUniversity of Pennsylvania via Coursera\u2605\u2605\u2606\u2606\u2606 (1 rating) Robotics: PerceptionUniversity of Pennsylvania via Coursera\u2605\u2605\u2605\u2606\u2606 (2 ratings) Robotics: MobilityUniversity of Pennsylvania via Coursera RoboticsColumbia University via edX If you enjoyed reading this, check out some of Class Central\u2019s other pieces: ", "author": "Dhawal Shah", "sentences": [{"5145": "Here are 250 Ivy League courses you can take online right now for\u00a0free"}, {"d055": "The 8 Ivy League schools are among the most prestigious colleges in the world. They include Brown, Harvard, Cornell, Princeton, Dartmouth, Yale, and Columbia universities, and the University of Pennsylvania."}, {"5a84": "All eight schools place in the top fifteen of the U.S. News and World Report 2017 national university rankings."}, {"89c5": "These Ivy League schools are also highly selective and extremely hard to get into. But the good news is that all these universities now offer free online courses across multiple online course platforms."}, {"bd3b": "So far, they\u2019ve created over 300 courses, of which around 250 are still active. Class Central has made a collection of all these, which you can explore below. I\u2019ve split these courses into the following categories:"}, {"d174": "I\u2019ve also assembled these courses on Class Central\u2019s collection page for Ivy League MOOCs. This collection gets updated automatically as new courses are added. You can subscribe to receive updates by clicking the blue \u201cfollow\u201d button there."}, {"7658": "Ivy League MOOCs collection on Class\u00a0Central"}, {"f466": "You can also watch Quincy Larson\u2019s interview with me about this article."}, {"05c9": "Computer Science (28\u00a0courses)"}, {"65d1": "Introduction to Computer ScienceHarvard University via edX\u2605\u2605\u2605\u2605\u2605 (52 ratings)"}, {"1c86": "Algorithms, Part IPrinceton University via Coursera\u2605\u2605\u2605\u2605\u2606 (48 ratings)"}, {"1295": "Machine LearningGeorgia Institute of Technology via Udacity\u2605\u2605\u2605\u2605\u2605 (4 ratings)"}, {"a5ee": "Analysis of AlgorithmsPrinceton University via Coursera\u2605\u2605\u2605\u2605\u2605 (4 ratings)"}, {"4ffc": "Bitcoin and Cryptocurrency TechnologiesPrinceton University via Coursera\u2605\u2605\u2605\u2605\u2606 (10 ratings)"}, {"f1d8": "Introduction to Spreadsheets and ModelsUniversity of Pennsylvania via Coursera\u2605\u2605\u2605\u2605\u2605 (3 ratings)"}, {"a9e3": "Computer ArchitecturePrinceton University via Coursera\u2605\u2605\u2605\u2605\u2605 (4 ratings)"}, {"69c3": "Machine LearningBrown University via Udacity\u2605\u2605\u2605\u2605\u2605 (1 rating)"}, {"68db": "Networks Illustrated: Principles without CalculusPrinceton University via Coursera\u2605\u2605\u2605\u2605\u2606 (3 ratings)"}, {"acfb": "Software Defined NetworkingPrinceton University via Coursera\u2605\u2605\u2605\u2605\u2606 (5 ratings)"}, {"6d03": "Machine Learning 1\u200a\u2014\u200aSupervised LearningBrown University via Udacity\u2605\u2605\u2605\u2605\u2606 (1 rating)"}, {"8c6f": "Machine Learning: Unsupervised LearningBrown University via Udacity\u2605\u2605\u2605\u2605\u2606 (1 rating)"}, {"d513": "Introduction to Bioconductor: Annotation and Analysis of Genomes and Genomic AssaysHarvard University via edX\u2605\u2605\u2605\u2605\u2606 (1 rating)"}, {"1282": "Statistics and RHarvard University via edX\u2605\u2605\u2605\u2605\u2606 (13 ratings)"}, {"e7c8": "Networks: Friends, Money, and BytesPrinceton University via Coursera\u2605\u2605\u2605\u2606\u2606 (1 rating)"}, {"4944": "The Computing Technology Inside Your SmartphoneCornell University via edX\u2605\u2605\u2605\u2605\u2605 (2 ratings)"}, {"c906": "Using Python for ResearchHarvard University via edX"}, {"22f0": "Case Studies in Functional GenomicsHarvard University via edX\u2605\u2605\u2605\u2606\u2606 (1 rating)"}, {"da86": "Machine Learning for Data Science and AnalyticsColumbia University via edX\u2605\u2605\u2605\u2606\u2606 (15 ratings)"}, {"79ea": "Reinforcement LearningBrown University via Udacity\u2605\u2605\u2606\u2606\u2606 (6 ratings)"}, {"f34e": "Enabling Technologies for Data Science and Analytics: The Internet of ThingsColumbia University via edX\u2605\u2606\u2606\u2606\u2606 (5 ratings)"}, {"3643": "Statistical Thinking for Data Science and AnalyticsColumbia University via edX\u2605\u2605\u2606\u2606\u2606 (13 ratings)"}, {"7635": "Artificial Intelligence (AI)Columbia University via edX\u2605\u2606\u2606\u2606\u2606 (1 rating)"}, {"22ab": "Machine LearningColumbia University via edX"}, {"505d": "Big Data in EducationColumbia University via edX"}, {"bb95": "High-performance Computing for Reproducible GenomicsHarvard University via edX"}, {"af4e": "AP\u00ae Computer Science PrinciplesHarvard University via edX"}, {"ff07": "Animation and CGI MotionColumbia University via edX"}, {"801e": "Humanities (44\u00a0courses)"}, {"2442": "Modern & Contemporary American Poetry (\u201cModPo\u201d)University of Pennsylvania via Coursera\u2605\u2605\u2605\u2605\u2605 (128 ratings)"}, {"f2d7": "Moralities of Everyday LifeYale University via Coursera\u2605\u2605\u2605\u2605\u2605 (31 ratings)"}, {"0fbc": "The Civil War and Reconstruction\u200a\u2014\u200a1865\u20131890: The Unfinished RevolutionColumbia University via edX\u2605\u2605\u2605\u2605\u2605 (5 ratings)"}, {"cc23": "Ancient Philosophy: Plato & His PredecessorsUniversity of Pennsylvania via Coursera\u2605\u2605\u2605\u2605\u2605 (9 ratings)"}, {"c32e": "The Civil War and Reconstruction\u200a\u2014\u200a1861\u20131865: A New Birth of FreedomColumbia University via edX\u2605\u2605\u2605\u2605\u2605 (4 ratings)"}, {"d6e4": "The Civil War and Reconstruction\u200a\u2014\u200a1850\u20131861: A Nation DividedColumbia University via edX\u2605\u2605\u2605\u2605\u2605 (5 ratings)"}, {"04ab": "American Capitalism: A HistoryCornell University via edX\u2605\u2605\u2605\u2605\u2605 (3 ratings)"}, {"df5c": "Visualizing Japan (1850s-1930s): Westernization, Protest, ModernityHarvard University via edX\u2605\u2605\u2605\u2605\u2605 (5 ratings)"}, {"8d74": "Greek and Roman MythologyUniversity of Pennsylvania via Coursera\u2605\u2605\u2605\u2605\u2606 (11 ratings)"}, {"e8a6": "Introduction to Ancient Egypt and Its CivilizationUniversity of Pennsylvania via Coursera\u2605\u2605\u2605\u2605\u2605 (1 rating)"}, {"a7dd": "The Book: Books in the Medieval LiturgyHarvard University via edX\u2605\u2605\u2605\u2605\u2605 (1 rating)"}, {"38af": "Buddhism Through Its ScripturesHarvard University via edX\u2605\u2605\u2605\u2605\u2605 (1 rating)"}, {"0060": "PredictionX: John Snow and the Cholera Epidemic of 1854Harvard University via edX\u2605\u2605\u2605\u2605\u2605 (1 rating)"}, {"c2a0": "Effective AltruismPrinceton University via Coursera\u2605\u2605\u2605\u2605\u2605 (2 ratings)"}, {"6030": "The Ethics of EatingCornell University via edX\u2605\u2605\u2605\u2605\u2605 (2 ratings)"}, {"74c3": "Religious Literacy: Traditions and ScripturesHarvard University via edX\u2605\u2605\u2605\u2605\u2606 (3 ratings)"}, {"b6df": "Journey of the Universe: The Unfolding of LifeYale University via Coursera\u2605\u2605\u2605\u2605\u2606 (1 rating)"}, {"ace6": "Ancient Philosophy: Aristotle and His SuccessorsUniversity of Pennsylvania via Coursera\u2605\u2605\u2605\u2605\u2606 (7 ratings)"}, {"9983": "Christianity Through Its ScripturesHarvard University via edX\u2605\u2605\u2605\u2605\u2606 (2 ratings)"}, {"9f4a": "Masterpieces of World LiteratureHarvard University via edX\u2605\u2605\u2605\u2606\u2606 (1 rating)"}, {"8d8b": "The Book: The Medieval Book of Hours: Art and Devotion in the Later Middle AgesHarvard University via edX\u2605\u2605\u2605\u2606\u2606 (2 ratings)"}, {"e90b": "The Ancient Greek Hero in 24 HoursHarvard University via edX\u2605\u2605\u2605\u2606\u2606 (2 ratings)"}, {"0b6b": "China (Part 1): Political and Intellectual Foundations: From the Sage Kings to Confucius and the LegalistsHarvard University via edX\u2605\u2605\u2605\u2605\u2605 (7 ratings)"}, {"5b33": "China (Part 2): The Creation and End of Centralized EmpireHarvard University via edX\u2605\u2605\u2605\u2605\u2605 (6 ratings)"}, {"0f43": "China (Part 3): Cosmopolitan Tang: Aristocratic CultureHarvard University via edX\u2605\u2605\u2605\u2605\u2605 (4 ratings)"}, {"d361": "China (Part 4): Literati China: Examinations and Neo-ConfucianismHarvard University via edX\u2605\u2605\u2605\u2605\u2605 (6 ratings)"}, {"b187": "China (Part 5): From a Global Empire under the Mongols to a Global Economy under the Ming DynastyHarvard University via edX\u2605\u2605\u2605\u2605\u2605 (4 ratings)"}, {"00a5": "China (Part 6): The Manchus and the Qing DynastyHarvard University via edX\u2605\u2605\u2605\u2605\u2605 (6 ratings)"}, {"b749": "China (Part 7): Invasions, Rebellions and the Fall of Imperial ChinaHarvard University via edX\u2605\u2605\u2605\u2605\u2605 (4 ratings)"}, {"7713": "China (Part 8): Creating Modern China: The Birth of a NationHarvard University via edX\u2605\u2605\u2605\u2605\u2605 (5 ratings)"}, {"63ec": "China (Part 9): China and CommunismHarvard University via edX\u2605\u2605\u2605\u2605\u2605 (4 ratings)"}, {"5af6": "China (Part 10): Greater China Today: The People\u2019s Republic, Taiwan, and Hong KongHarvard University via edX\u2605\u2605\u2605\u2605\u2605 (4 ratings)"}, {"d931": "English for JournalismUniversity of Pennsylvania via Coursera"}, {"46cc": "English for Career DevelopmentUniversity of Pennsylvania via Coursera"}, {"dc67": "The Worldview of Thomas Berry: The Flourishing of the Earth CommunityYale University via Coursera"}, {"d84f": "Question Reality! Science, philosophy, and the search for meaningDartmouth via edX"}, {"3bf9": "The Book: Book Sleuthing: What 19th-Century Books Can Tell Us About the Rise of the Reading Public?Harvard University via edX"}, {"49c7": "Writing Case Studies: Science of DeliveryPrinceton University via edX"}, {"b9af": "The American Renaissance: Classic Literature of the 19th CenturyDartmouth via edX"}, {"beeb": "Islam Through Its ScripturesHarvard University via edX"}, {"351c": "Hinduism Through Its ScripturesHarvard University via edX"}, {"95c6": "Judaism Through Its ScripturesHarvard University via edX"}, {"fbee": "Hamlet\u2019s GhostHarvard University via edX"}, {"91cd": "English for Business and EntrepreneurshipUniversity of Pennsylvania via Coursera"}, {"ba69": "Social Sciences (37\u00a0courses)"}, {"960a": "JusticeHarvard University via edX\u2605\u2605\u2605\u2605\u2605 (27 ratings)"}, {"eb6b": "An Introduction to American LawUniversity of Pennsylvania via Coursera\u2605\u2605\u2605\u2605\u2605 (13 ratings)"}, {"e39b": "Introduction to Key Constitutional Concepts and Supreme Court CasesUniversity of Pennsylvania via Coursera\u2605\u2605\u2605\u2605\u2605 (5 ratings)"}, {"7306": "The Book: Making and Meaning in the Medieval ManuscriptHarvard University via edX\u2605\u2605\u2605\u2605\u2605 (3 ratings)"}, {"b7bb": "America\u2019s Unwritten ConstitutionYale University via Coursera\u2605\u2605\u2605\u2605\u2605 (3 ratings)"}, {"04d8": "Buddhism and Modern Psychology Princeton University via Coursera\u2605\u2605\u2605\u2605\u2606 (19 ratings)"}, {"bde8": "Tangible Things: Discovering History Through Artworks, Artifacts, Scientific Specimens, and the Stuff Around YouHarvard University via edX\u2605\u2605\u2605\u2605\u2605 (5 ratings)"}, {"dfb2": "Moral Foundations of Politics Yale University via Coursera\u2605\u2605\u2605\u2605\u2606 (11 ratings)"}, {"14c5": "The Book: Monasteries, Schools, and Notaries, Part 2: Introduction to the Transitional Gothic ScriptHarvard University via edX\u2605\u2605\u2605\u2605\u2605 (2 ratings)"}, {"7d87": "Contract Law: From Trust to Promise to ContractHarvard University via edX\u2605\u2605\u2605\u2605\u2606 (7 ratings)"}, {"1626": "Microeconomics: When Markets FailUniversity of Pennsylvania via Coursera\u2605\u2605\u2605\u2605\u2605 (1 rating)"}, {"2acb": "The Book: Print and Manuscript in Western Europe, Asia and the Middle East (1450\u20131650)Harvard University via edX\u2605\u2605\u2605\u2605\u2605 (1 rating)"}, {"f1a5": "The Book: The History of the Book in the 17th and 18th Century EuropeHarvard University via edX\u2605\u2605\u2605\u2605\u2605 (1 rating)"}, {"56ec": "The Book: Scrolls in the Age of the BookHarvard University via edX\u2605\u2605\u2605\u2605\u2605 (1 rating)"}, {"197b": "Intellectual Property Law and Policy\u200a\u2014\u200aPart 1: IP and Patent LawsUniversity of Pennsylvania via edX\u2605\u2605\u2605\u2605\u2605 (1 rating)"}, {"4680": "The History of Medieval Medicine Through Jewish ManuscriptsUniversity of Pennsylvania via edX\u2605\u2605\u2605\u2605\u2605 (1 rating)"}, {"b9fe": "JuryX: Deliberations for Social ChangeHarvard University via edX\u2605\u2605\u2605\u2605\u2605 (2 ratings)"}, {"df32": "Revolutionary Ideas: Utility, Justice, Equality, FreedomUniversity of Pennsylvania via Coursera\u2605\u2605\u2605\u2605\u2606 (3 ratings)"}, {"884b": "American GovernmentHarvard University via edX\u2605\u2605\u2605\u2605\u2606 (3 ratings)"}, {"f7a5": "Paradoxes of WarPrinceton University via Coursera\u2605\u2605\u2605\u2605\u2606 (9 ratings)"}, {"6a7f": "America\u2019s Written ConstitutionYale University via Coursera\u2605\u2605\u2605\u2605\u2606 (8 ratings)"}, {"3bf6": "A Law Student\u2019s ToolkitYale University via Coursera\u2605\u2605\u2605\u2605\u2606 (1 rating)"}, {"2a9e": "The Book: Monasteries, Schools, and Notaries, Part 1: Reading the Late Medieval Marseille ArchiveHarvard University via edX\u2605\u2605\u2605\u2605\u2606 (3 ratings)"}, {"e886": "Intellectual Property Law and Policy\u200a\u2014\u200aPart 2: Copyright and Trademark LawsUniversity of Pennsylvania via edX\u2605\u2605\u2605\u2605\u2606 (1 rating)"}, {"a5bb": "Bioethics: The Law, Medicine, and Ethics of Reproductive Technologies and GeneticsHarvard University via edX\u2605\u2605\u2605\u2605\u2606 (2 ratings)"}, {"b3da": "Microeconomics: The Power of MarketsUniversity of Pennsylvania via Coursera\u2605\u2605\u2605\u2605\u2606 (5 ratings)"}, {"c167": "Introduction to SociologyPrinceton University via Coursera\u2605\u2605\u2605\u2605\u2606 (4 ratings)"}, {"32c5": "Wiretaps to Big Data: Privacy and Surveillance in the Age of InterconnectionCornell University via edX\u2605\u2605\u2605\u2606\u2606 (1 rating)"}, {"76ab": "Central Challenges of American National Security, Strategy, and the PressHarvard University via edX\u2605\u2605\u2605\u2606\u2606 (1 rating)"}, {"7707": "Networks, Crowds and MarketsCornell University via edX\u2605\u2605\u2606\u2606\u2606 (1 rating)"}, {"2284": "Top 10 Social Issues for the President\u2019s First 100 DaysUniversity of Pennsylvania via edX"}, {"62a2": "CorruptionUniversity of Pennsylvania via Coursera"}, {"3570": "Revolutionary Ideas: Borders, Elections, Constitutions, PrisonsUniversity of Pennsylvania via Coursera"}, {"34bc": "Social Norms, Social Change IUniversity of Pennsylvania via Coursera"}, {"1ce7": "Social Norms, Social Change IIUniversity of Pennsylvania via Coursera"}, {"b2d8": "Making Government Work in Hard PlacesPrinceton University via edX"}, {"02d8": "Freedom of Expression in the Age of GlobalizationColumbia University via edX"}, {"9e2a": "Art & Design (16\u00a0courses)"}, {"df55": "Introduction to Classical MusicYale University via Coursera\u2605\u2605\u2605\u2605\u2605 (14 ratings)"}, {"401e": "GamificationUniversity of Pennsylvania via Coursera\u2605\u2605\u2605\u2605\u2606 (52 ratings)"}, {"0a32": "Design: Creation of Artifacts in SocietyUniversity of Pennsylvania via Coursera\u2605\u2605\u2605\u2605\u2605 (13 ratings)"}, {"f449": "First Nights: Handel\u2019s Messiah and Baroque OratorioHarvard University via edX\u2605\u2605\u2605\u2605\u2605 (1 rating)"}, {"1c3d": "First Nights: Beethoven\u2019s 9th Symphony and the 19th Century OrchestraHarvard University via edX\u2605\u2605\u2605\u2605\u2605 (1 rating)"}, {"da56": "First Nights: Monteverdi\u2019s L\u2019Orfeo and the Birth of OperaHarvard University via edX\u2605\u2605\u2605\u2605\u2605 (1 rating)"}, {"007e": "First Nights: Berlioz\u2019s Symphonie Fantastique and Program Music in the 19th CenturyHarvard University via edX\u2605\u2605\u2605\u2605\u2605 (1 rating)"}, {"9aca": "Hollywood: History, Industry, ArtUniversity of Pennsylvania via edX\u2605\u2605\u2605\u2605\u2605 (1 rating)"}, {"5ea7": "First Nights: Igor Stravinsky\u2019s The Rite of Spring: Modernism, Ballet, and RiotsHarvard University via edX\u2605\u2605\u2605\u2605\u2606 (1 rating)"}, {"d1da": "Music and Social ActionYale University via Coursera\u2605\u2605\u2605\u2605\u2606 (1 rating)"}, {"1d5e": "Listening to World MusicUniversity of Pennsylvania via Coursera\u2605\u2605\u2605\u2605\u2606 (3 ratings)"}, {"c469": "Introduction to Italian OperaDartmouth via edX\u2605\u2605\u2605\u2606\u2606 (2 ratings)"}, {"2212": "The Architectural ImaginationHarvard University via edX"}, {"f281": "The History of Music Production TechniquesColumbia University via Kadenze"}, {"1cab": "Introduction to German OperaDartmouth via edX"}, {"3188": "Reinventing the PianoPrinceton University via Kadenze"}, {"16ae": "Science (19\u00a0courses)"}, {"0049": "The Age of Sustainable DevelopmentColumbia University via Coursera\u2605\u2605\u2605\u2605\u2605 (11 ratings)"}, {"f9f5": "Science & Cooking: From Haute Cuisine to Soft Matter Science (part 1)Harvard University via edX\u2605\u2605\u2605\u2605\u2605 (7 ratings)"}, {"0f68": "Principles of BiochemistryHarvard University via edX\u2605\u2605\u2605\u2605\u2605 (3 ratings)"}, {"9e90": "Fundamentals of Neuroscience Part 2: Neurons and NetworksHarvard University via edX\u2605\u2605\u2605\u2605\u2605 (3 ratings)"}, {"a0f1": "Introduction to Sustainable DevelopmentColumbia University via Coursera\u2605\u2605\u2605\u2605\u2605 (7 ratings)"}, {"3b4d": "Super-Earths And LifeHarvard University via edX\u2605\u2605\u2605\u2605\u2605 (4 ratings)"}, {"ba92": "Fundamentals of Neuroscience Part 1: Electrical Properties of the NeuronHarvard University via edX\u2605\u2605\u2605\u2605\u2606 (7 ratings)"}, {"3e16": "Sharks! Global Biodiversity, Biology, and ConservationCornell University via edX\u2605\u2605\u2605\u2605\u2605 (1 rating)"}, {"b49b": "The Fundamentals of Neuroscience Part 3: The BrainHarvard University via edX\u2605\u2605\u2605\u2605\u2605 (1 rating)"}, {"22e3": "AnatomyX: Musculoskeletal CasesHarvard University via edX\u2605\u2605\u2605\u2605\u2605 (2 ratings)"}, {"3a1a": "Introduction to Environmental ScienceDartmouth via edX\u2605\u2605\u2605\u2605\u2606 (5 ratings)"}, {"a80b": "Imagining Other EarthsPrinceton University via Coursera\u2605\u2605\u2605\u2605\u2606 (1 rating)"}, {"b39c": "High-Dimensional Data AnalysisHarvard University via edX\u2605\u2605\u2605\u2605\u2606 (3 ratings)"}, {"1ba8": "Relativity and AstrophysicsCornell University via edX\u2605\u2605\u2605\u2605\u2606 (5 ratings)"}, {"8093": "The Einstein RevolutionHarvard University via edX\u2605\u2605\u2606\u2606\u2606 (1 rating)"}, {"7836": "Cell Biology: MitochondriaHarvard University via edX\u2605\u2605\u2606\u2606\u2606 (1 rating)"}, {"d180": "Basic Behavioral NeurologyUniversity of Pennsylvania via Coursera\u2605\u2605\u2606\u2606\u2606 (4 ratings)"}, {"631c": "Journey Conversations: Weaving Knowledge and ActionYale University via Coursera"}, {"54fa": "Sustainability, Resilience, and SocietyHarvard University via edX"}, {"66e8": "Health & Medicine(19 subjects)"}, {"5f6c": "Vital Signs: Understanding What the Body Is Telling UsUniversity of Pennsylvania via Coursera\u2605\u2605\u2605\u2605\u2605 (34 ratings)"}, {"20b1": "Introduction to Breast CancerYale University via Coursera\u2605\u2605\u2605\u2605\u2605 (2 ratings)"}, {"a7da": "Readings in Global HealthHarvard University via edX\u2605\u2605\u2605\u2605\u2605 (1 rating)"}, {"485b": "Health and SocietyHarvard University via edX\u2605\u2605\u2605\u2605\u2605 (1 rating)"}, {"a79b": "Global Health Case Studies from a Biosocial PerspectiveHarvard University via edX\u2605\u2605\u2605\u2605\u2605 (1 rating)"}, {"39a8": "Improving Global Health: Focusing on Quality and SafetyHarvard University via edX\u2605\u2605\u2605\u2605\u2606 (3 ratings)"}, {"1d04": "Introduction to Dental MedicineUniversity of Pennsylvania via Coursera\u2605\u2605\u2605\u2605\u2606 (4 ratings)"}, {"d512": "Fundamentals of PharmacologyUniversity of Pennsylvania via Coursera\u2605\u2605\u2605\u2605\u2606 (6 ratings)"}, {"52fc": "United States Health PolicyHarvard University via edX\u2605\u2605\u2605\u2605\u2605 (2 ratings)"}, {"81e4": "Going Out on a Limb: Anatomy of the Upper LimbUniversity of Pennsylvania via edX\u2605\u2605\u2605\u2605\u2606 (2 ratings)"}, {"c0ff": "Humanitarian Response to Conflict and DisasterHarvard University via edX\u2605\u2605\u2605\u2605\u2606 (1 rating)"}, {"e9dc": "PH556X: Practical Improvement Science in Health Care: A Roadmap for Getting ResultsHarvard University via edX"}, {"985a": "HI-FIVE: Health Informatics For Innovation, Value & Enrichment (Clinical Perspective)Columbia University via Coursera"}, {"0603": "Fundamentals of Clinical TrialsHarvard University via edX"}, {"e3dd": "Innovating in Health CareHarvard University via edX"}, {"69a6": "Lessons from Ebola: Preventing the Next PandemicHarvard University via edX"}, {"8b67": "The Opioid Crisis in AmericaHarvard University via edX"}, {"a7d3": "The Science and Politics of the GMOCornell University via edX"}, {"eedd": "Essentials of Global HealthYale University via Coursera"}, {"ac06": "Business & Management (46\u00a0courses)"}, {"9c4b": "Introduction to Financial AccountingUniversity of Pennsylvania via Coursera\u2605\u2605\u2605\u2605\u2605 (38 ratings)"}, {"ad94": "Introduction to MarketingUniversity of Pennsylvania via Coursera\u2605\u2605\u2605\u2605\u2606 (47 ratings)"}, {"b039": "Introduction to Corporate FinanceWharton School of the University of Pennsylvania via Coursera\u2605\u2605\u2605\u2605\u2606 (16 ratings)"}, {"5a1c": "A Preview Course on The 5 Killer Risks of Enterprise Risk ManagementColumbia University via Canvas Network\u2605\u2605\u2605\u2605\u2605 (3 ratings)"}, {"45d5": "Introduction to Negotiation: A Strategic Playbook for Becoming a Principled and Persuasive NegotiatorYale University via Coursera\u2605\u2605\u2605\u2605\u2605 (2 ratings)"}, {"30d4": "The Global Financial CrisisYale University via Coursera\u2605\u2605\u2605\u2605\u2606 (9 ratings)"}, {"af55": "Arts and Culture StrategyUniversity of Pennsylvania via Coursera\u2605\u2605\u2605\u2605\u2605 (2 ratings)"}, {"f82c": "Operations AnalyticsUniversity of Pennsylvania via Coursera\u2605\u2605\u2605\u2605\u2605 (4 ratings)"}, {"f05b": "Financial MarketsYale University via Coursera\u2605\u2605\u2605\u2605\u2606 (21 ratings)"}, {"8c6a": "Introducci\u00f3n al MarketingUniversity of Pennsylvania via Coursera\u2605\u2605\u2605\u2605\u2605 (1 rating)"}, {"1384": "Financial Engineering and Risk Management Part IColumbia University via Coursera\u2605\u2605\u2605\u2605\u2606 (10 ratings)"}, {"eab1": "Introduction to Operations ManagementWharton School of the University of Pennsylvania via Coursera\u2605\u2605\u2605\u2605\u2606 (29 ratings)"}, {"f1e6": "Entrepreneurship 4: Financing and ProfitabilityUniversity of Pennsylvania via Coursera\u2605\u2605\u2605\u2605\u2606 (3 ratings)"}, {"cbde": "Financial Engineering and Risk Management Part IIColumbia University via Coursera\u2605\u2605\u2605\u2605\u2606 (3 ratings)"}, {"3bcb": "Entrepreneurship 2: Launching your Start-UpUniversity of Pennsylvania via Coursera\u2605\u2605\u2605\u2605\u2606 (4 ratings)"}, {"dbb6": "More Introduction to Financial AccountingUniversity of Pennsylvania via Coursera\u2605\u2605\u2605\u2605\u2606 (4 ratings)"}, {"dc8f": "Entrepreneurship 1: Developing the OpportunityUniversity of Pennsylvania via Coursera\u2605\u2605\u2605\u2605\u2606 (4 ratings)"}, {"ff31": "Global Human Capital TrendsColumbia University via Canvas Network\u2605\u2605\u2605\u2605\u2606 (5 ratings)"}, {"f047": "People AnalyticsUniversity of Pennsylvania via Coursera\u2605\u2605\u2605\u2605\u2606 (4 ratings)"}, {"4e6d": "Social Impact Strategy: Tools for Entrepreneurs and InnovatorsUniversity of Pennsylvania via Coursera\u2605\u2605\u2605\u2605\u2606 (4 ratings)"}, {"9556": "Introduction to Global Hospitality ManagementCornell University via edX\u2605\u2605\u2605\u2605\u2606 (2 ratings)"}, {"2e25": "Fundamentals of Quantitative ModelingUniversity of Pennsylvania via Coursera\u2605\u2605\u2605\u2605\u2606 (2 ratings)"}, {"4f3c": "Accounting AnalyticsUniversity of Pennsylvania via Coursera\u2605\u2605\u2605\u2605\u2606 (5 ratings)"}, {"2e36": "Viral Marketing and How to Craft Contagious ContentUniversity of Pennsylvania via Coursera\u2605\u2605\u2605\u2605\u2606 (5 ratings)"}, {"f794": "Construction SchedulingColumbia University via Coursera\u2605\u2606\u2606\u2606\u2606 (1 rating)"}, {"b872": "Customer AnalyticsUniversity of Pennsylvania via Coursera\u2605\u2605\u2605\u2606\u2606 (14 ratings)"}, {"6354": "Construction FinanceColumbia University via Coursera"}, {"1d98": "Building High-Performing TeamsUniversity of Pennsylvania via Coursera"}, {"28f7": "Managing Social and Human CapitalUniversity of Pennsylvania via Coursera"}, {"b4a9": "Decision-Making and ScenariosUniversity of Pennsylvania via Coursera"}, {"ee14": "Construction Project ManagementColumbia University via Coursera"}, {"e0e4": "Entrepreneurship and Healthcare in Emerging EconomiesHarvard University via edX"}, {"b838": "Digital Marketing, Social Media and E-Commerce for Your BusinessUniversity of Pennsylvania via edX"}, {"1542": "Entrepreneurship in Emerging EconomiesHarvard University via edX"}, {"fdb8": "The Power of Team CultureUniversity of Pennsylvania via Coursera"}, {"9d6d": "Optimizing Diversity on TeamsUniversity of Pennsylvania via Coursera"}, {"22ee": "Creating a Team Culture of Continuous LearningUniversity of Pennsylvania via Coursera"}, {"3fac": "\u4f01\u4e1a\u91d1\u878d\u6982\u8bba\uff08\u4e2d\u6587\u7248\uff09University of Pennsylvania via Coursera"}, {"d0ec": "\u5e02\u573a\u8425\u9500\u6982\u8bba (\u4e2d\u6587\u7248\uff09University of Pennsylvania via Coursera"}, {"b658": "Introducci\u00f3n a la Contabilidad FinancieraUniversity of Pennsylvania via Coursera"}, {"e18c": "\u8fd0\u8425\u7ba1\u7406\u6982\u8bba\uff08\u4e2d\u6587\u7248\uff09University of Pennsylvania via Coursera"}, {"86ff": "Introducci\u00f3n a la Gesti\u00f3n de OperacionesUniversity of Pennsylvania via Coursera"}, {"918e": "Modeling Risk and RealitiesUniversity of Pennsylvania via Coursera"}, {"0fc1": "\u8d22\u52a1\u4f1a\u8ba1\u6982\u8bba\uff08\u4e2d\u6587\u7248\uff09University of Pennsylvania via Coursera"}, {"a1b5": "Introducci\u00f3n a las Finanzas CorporativasUniversity of Pennsylvania via Coursera"}, {"3189": "Construction Cost Estimating and Cost ControlColumbia University via Coursera"}, {"96f5": "Innovate on DemandColumbia University via Coursera"}, {"efaa": "A Preview Course on Collaborative Knowledge ServicesColumbia University via Canvas Network\u2605\u2605\u2605\u2605\u2605 (2 ratings)"}, {"700d": "SuccessUniversity of Pennsylvania via Coursera"}, {"3dcb": "Mathematics (8\u00a0courses)"}, {"86c0": "Calculus: Single Variable Part 1\u200a\u2014\u200aFunctionsUniversity of Pennsylvania via Coursera\u2605\u2605\u2605\u2605\u2605 (5 ratings)"}, {"3275": "Calculus: Single Variable Part 2\u200a\u2014\u200aDifferentiationUniversity of Pennsylvania via Coursera\u2605\u2605\u2605\u2605\u2605 (4 ratings)"}, {"be68": "Introduction to Linear Models and Matrix AlgebraHarvard University via edX\u2605\u2605\u2605\u2605\u2605 (8 ratings)"}, {"0508": "Calculus: Single Variable Part 4\u200a\u2014\u200aApplicationsUniversity of Pennsylvania via Coursera\u2605\u2605\u2605\u2605\u2605 (3 ratings)"}, {"c7d2": "Statistical Inference and Modeling for High-throughput ExperimentsHarvard University via edX\u2605\u2605\u2605\u2605\u2605 (3 ratings)"}, {"24c3": "Calculus: Single Variable Part 3\u200a\u2014\u200aIntegrationUniversity of Pennsylvania via Coursera\u2605\u2605\u2605\u2605\u2606 (4 ratings)"}, {"abcc": "Analytic CombinatoricsPrinceton University via Coursera\u2605\u2605\u2605\u2605\u2606 (2 ratings)"}, {"2c43": "Single Variable CalculusUniversity of Pennsylvania via Coursera"}, {"47e1": "Education & Teaching (14\u00a0courses)"}, {"2010": "American Education Reform: History, Policy, PracticeUniversity of Pennsylvania via Coursera\u2605\u2605\u2605\u2605\u2605 (8 ratings)"}, {"4be5": "Leaders of LearningHarvard University via edX\u2605\u2605\u2605\u2605\u2606 (12 ratings)"}, {"69ad": "Saving Schools, Mini-Course 1: History and Politics of U.S. EducationHarvard University via edX\u2605\u2605\u2605\u2605\u2606 (3 ratings)"}, {"d3ec": "Saving Schools, Mini-Course 2: Teacher PoliciesHarvard University via edX\u2605\u2605\u2605\u2605\u2606 (1 rating)"}, {"cfd1": "Saving Schools, Mini-Course 3: Accountability and National StandardsHarvard University via edX\u2605\u2605\u2605\u2605\u2606 (1 rating)"}, {"b752": "Saving Schools, Mini-Course 4: School ChoiceHarvard University via edX\u2605\u2605\u2605\u2605\u2606 (1 rating)"}, {"9d09": "Applying to U.S. UniversitiesUniversity of Pennsylvania via Coursera\u2605\u2605\u2605\u2605\u2606 (10 ratings)"}, {"a3c7": "How to Apply to CollegeUniversity of Pennsylvania via Coursera"}, {"6605": "Introduction to Data Wise: A Collaborative Process to Improve Learning & TeachingHarvard University via edX"}, {"fbac": "Introduction to Family Engagement in EducationHarvard University via edX"}, {"8b95": "Understanding Classroom InteractionUniversity of Pennsylvania via edX"}, {"0e59": "The Science of Learning\u200a\u2014\u200aWhat Every Teacher Should KnowColumbia University via edX"}, {"2c8e": "English for Science, Technology, Engineering, and MathematicsUniversity of Pennsylvania via Coursera"}, {"8db2": "Orchestrating Whole Classroom DiscussionUniversity of Pennsylvania via Coursera"}, {"2123": "Engineering (13\u00a0courses)"}, {"91e6": "The Engineering of Structures Around UsDartmouth via edX\u2605\u2605\u2605\u2605\u2605 (2 ratings)"}, {"a965": "A Hands-on Introduction to Engineering SimulationsCornell University via edX\u2605\u2605\u2605\u2605\u2605 (2 ratings)"}, {"b5db": "The Art of Structural Engineering: BridgesPrinceton University via edX\u2605\u2605\u2605\u2605\u2605 (3 ratings)"}, {"0010": "Designing CitiesUniversity of Pennsylvania via Coursera\u2605\u2605\u2605\u2605\u2606 (6 ratings)"}, {"7a6d": "MOS TransistorsColumbia University via Coursera\u2605\u2605\u2605\u2605\u2605 (1 rating)"}, {"53bc": "Energy Within Environmental ConstraintsHarvard University via edX\u2605\u2605\u2605\u2605\u2605 (1 rating)"}, {"73f4": "Robotics: Aerial RoboticsUniversity of Pennsylvania via Coursera\u2605\u2605\u2605\u2605\u2606 (5 ratings)"}, {"f303": "Reclaiming Broken Places: Introduction to Civic EcologyCornell University via edX\u2605\u2605\u2605\u2606\u2606 (1 rating)"}, {"bd3d": "Robotics: Computational Motion PlanningUniversity of Pennsylvania via Coursera\u2605\u2605\u2606\u2606\u2606 (1 rating)"}, {"873d": "Robotics: Estimation and LearningUniversity of Pennsylvania via Coursera\u2605\u2605\u2606\u2606\u2606 (1 rating)"}, {"37b1": "Robotics: PerceptionUniversity of Pennsylvania via Coursera\u2605\u2605\u2605\u2606\u2606 (2 ratings)"}, {"72ff": "Robotics: MobilityUniversity of Pennsylvania via Coursera"}, {"765e": "RoboticsColumbia University via edX"}, {"b581": "If you enjoyed reading this, check out some of Class Central\u2019s other pieces:"}], "timestamp": "Feb 8", "parent": "", "child": "2445_1\t2445_2\t2445_3\t2445_4\t2445_5\t2445_6\t2445_7\t2445_8\t2445_9\t2445_10\t2445_11\t2445_12\t2445_13\t2445_14\t2445_15\t2445_16\t2445_17\t2445_18\t2445_19\t2445_20\t2445_21\t2445_22\t2445_23\t2445_24\t2445_25"}