{"name": "1030", "parent": "", "content": "Quando a gente sabe que \u00e9\u00a0amor? N\u00e3o \u00e9 num estalo m\u00e1gico. Ou\u00a0\u00e9? A Ana j\u00e1 estava na sexta rodada de cacha\u00e7a de banana, e no m\u00ednimo o dobro de cerveja, quando levantou uma quest\u00e3o important\u00edssima na mesa. \u2014 Rafa, quando a gente sabe que \u00e9\u00a0amor? A Ana tinha esse olhar perdido de quem olha para as estrelas como se olhasse uma pintura de Monet (sem entender porra nenhuma). Ela fazia isso agora, de modo que eu n\u00e3o sabia se a pergunta foi ret\u00f3rica ou se era pra mim mesma. \u2014 Mano, sei l\u00e1. Quando a gente fala eu te amo. Lembrei da vez que falei que amava o Zeca. Eu n\u00e3o amava ele, mas a mar\u00e9 mansa dos relacionamentos \u00e0s vezes nos puxa para o mar aberto, deixando somente a b\u00f3ia do \"eu te amo\" pra gente se segurar. A Ana percebeu meu erro de cara. \u2014 Rafa, n\u00e3o pode ser, cara. A gente fala que ama at\u00e9 pro gar\u00e7om.\u200a\u2014\u200aNisso, a Ana segurou gentilmente no bra\u00e7o do gar\u00e7om que passava\u200a\u2014\u200aTheo, eu te amo! \u2014 \u00d4, dona, a gente tamb\u00e9m te ama!\u200a\u2014\u200ae saiu. Gaitamos. Eu, que n\u00e3o queria ficar pra tr\u00e1s, pedi uma dose dupla de cachacinha. A Ana me acompanhou. Tentei puxar o papo pro lado de s\u00e9ries. N\u00e3o adiantou. \u2014 Rafa, \u00e9 s\u00e9rio. Quando a gente ama? Tipo, quando que a gente olha no espelho e fala \"fodeu, t\u00f4 amando\". \u2014 Quando a gente\u2026pensa na pessoa toda hora? \u2014 N\u00e3o, mano, isso \u00e9 obsess\u00e3o.\u200a\u2014\u200aAna passou a m\u00e3o pelos seus cabelos curtos e cor-de-rosa levemente\u200a\u2014\u200aeu queria ficar com o filha-da-puta do Andr\u00e9 toda hora. Mas eu era ing\u00eanua e ele mandava bem. Eu n\u00e3o amava ele, eu precisava. \u2014 Ele transava bem? \u2014 Uhum. O Thales foi assim, pra mim, mas eu n\u00e3o quis falar pra ela que j\u00e1 tinha transado com ele. Era primo dela, ela ia rir da minha cara. \u2014 U\u00e9, Ana. Onde voc\u00ea quer chegar? Voc\u00ea n\u00e3o t\u00e1 gostando mais do Gusta? \u2014 N\u00e3o, n\u00e3o. O Gusta \u00e9 \u00f3timo. \u00c9 legal, tem um papo cabe\u00e7a, n\u00e3o surta s\u00f3 de pensar em filhos e cozinha bem. Eu devia amar ele. E se p\u00e1 eu amo. Mas cad\u00ea a certeza?\u200a\u2014\u200aE novamente Ana cutuca o gar\u00e7om\u200a\u2014\u200aTheo, quando a gente sabe que \u00e9 amor de verdade? O gar\u00e7om, largando mais um litr\u00e3o gelado na mesa, que abre com um estampido, responde. \u2014 Quando traz cerveja gelada? Ca\u00edmos na risada novamente. \u2014 Cara, tipo, eu sei que eu amo meu trabalho. Eu amo ilustrar. Eu trabalho de casa, tem dia que eu come\u00e7o a trabalhar meia-noite e durmo at\u00e9 meio-dia. Eu tenho certeza que eu amo meu trabalho. Todo dia eu acordo e penso: \"caralho, eu faria isso at\u00e9 de gra\u00e7a se eu tivesse grana pra caralho\". Mas com relacionamento n\u00e3o. Eu nunca acordei todo dia pensando \"caralho, eu amo essa porra mais que minha vida toda!\". Durante o papo, comecei a me incomodar. A Ana sempre foi super aberta e tranquila pra falar que n\u00e3o amava os caras que ela estava, mas eu sempre amei os meus. Ou achava que amava. Para cada um dos namoros e casos-de-mais-de-um-m\u00eas deixei escapar um eu te amo aqui e outro ali. E tinha aquela certeza de Vin\u00edcius de Moraes de que eu havia amado cada um deles. Mas, nesse momento, comecei a separ\u00e1-los em caixinhas. Car\u00eancia. Amizade. Fase da vida. Resolvi me apegar nessa teoria para defender a minha pr\u00f3pria vida. \u2014 Ana, eu acho que amor \u00e9 uma palavra que inventaram pra agrupar um monte de sentimentos. Mesmo quando restringimos s\u00f3 para relacionamentos amorosos e sexuais, tem um monte de amor diferente. Car\u00eancia, amizade, fase da vida. Nem por isso \u00e9 menos amor. Acho que \u00e9 isso. \u2014 Voc\u00ea explicou o tipo. Mas quando que a gente sabe?\u200a\u2014\u200aAna disse, com a cacha\u00e7a fazendo com que ela se demorasse em algumas palavras. Sabe quando voc\u00ea se sentiu carente e\u200a\u2014\u200ap\u00e1!\u200a\u2014\u200aligou pro Ronaldo pra dar uns beijos e depois quis dizer que amava ele? Aquilo n\u00e3o deixa de ser amor. Naquele momento era amor. Amor n\u00e3o precisa ser daqui pra sempre, pode ser daqui pra daqui \u00e0 pouco. Pode largar um \"eu te amo\" sem medo.\u200a\u2014\u200aEncerrei t\u00e3o confiante que virei o copo de cerveja, devolvendo-o com estrondo para a mesa de metal. Ana, b\u00eabada como estava, levantou para me aplaudir. Sem querer, ela puxou um coro de \"Parab\u00e9ns \u00e0 Voc\u00ea\" no bar. N\u00e3o era meu anivers\u00e1rio. \u2014 Senta, idiota! Depois de mais risadas e mais uma rodada de cacha\u00e7a, Ana volta a me torrar a paci\u00eancia. \u2014 Rafa, voc\u00ea \u00e9 muito decidida. Voc\u00ea tem certeza que ama o L\u00e9o. \u00c0s vezes d\u00e1 vontade de ser mais assim. Tinha certeza? Eu nunca acordei em polvorosa por ele ter me amado ou estar comigo. Eu gostava da companhia dele e n\u00f3s combin\u00e1vamos em um monte de coisa. Era isso, e eu sempre achei que o nome disso era amor. At\u00e9 agora. \u2014 Ana, vira essa porra e para de fazer pergunta dif\u00edcil. Mais uma dose. Mais uma e mais uns litr\u00f5es. Deu a hora. Durante a volta pra casa o neg\u00f3cio bateu, a tontura chegou, o est\u00f4mago se inverteu. Cheguei em casa trope\u00e7ando, o L\u00e9o acordou. \u2014 Caralho, Rafa! Duas e meia e essa barulheira. \u2014 L\u00e9o, me azzuda aqui!\u200a\u2014\u200amal d\u00e1 tempo de chegar no banheiro. BLHAUSSSH. Tchau, tchau, cacha\u00e7a, cerveja e torresmo do bar. L\u00e9o segura meu cabelo. Vejo a risadinha de canto de boca do sacana. \u2014 Para de rir, seu sacana! \u2014 Tequila? \u2014 Teu cu!\u200a\u2014\u200aele sabia que eu odiava tequila. \u2014 Quer que eu fa\u00e7a um misto quente? Depois de me recompor, escovar os dentes e me ajeitar na cama. L\u00e9o chega trazendo o lanche. O teto girava. \u2014 Amor, eu vou ficar de muita ressaca amanh\u00e3? \u2014 Deixei um rem\u00e9dio e dois copos de \u00e1gua ali. Bebe um hoje e outro amanh\u00e3, com o rem\u00e9dio. Vai ficar zerada. O misto tava bom? \u2014 Sei l\u00e1. Ele vira e v\u00ea que consegui comer s\u00f3 metade. \u2014 Cuidado com as formigas nesse resto a\u00ed. Qualquer coisa grita.\u200a\u2014\u200ae virou pra dormir. Que hom\u00e3o da porra. \u2014 L\u00e9o, eu te amo. \u2014 Hmmmmm. E, sim, era amor mesmo. Pelo menos at\u00e9 chegar a ressaca. Se voc\u00ea gostou, deixa um \u2764\ufe0f a\u00ed. Isso faz com que o texto alcance mais\u00a0pessoas. Acompanhe todas as hist\u00f3rias da Revista Simbiose. ", "title": "Quando a gente sabe que \u00e9\u00a0amor?", "sentences": [{"4897": "Quando a gente sabe que \u00e9\u00a0amor?"}, {"7704": "N\u00e3o \u00e9 num estalo m\u00e1gico. Ou\u00a0\u00e9?"}, {"efa5": "A Ana j\u00e1 estava na sexta rodada de cacha\u00e7a de banana, e no m\u00ednimo o dobro de cerveja, quando levantou uma quest\u00e3o important\u00edssima na mesa."}, {"b417": "\u2014 Rafa, quando a gente sabe que \u00e9\u00a0amor?"}, {"540e": "A Ana tinha esse olhar perdido de quem olha para as estrelas como se olhasse uma pintura de Monet (sem entender porra nenhuma). Ela fazia isso agora, de modo que eu n\u00e3o sabia se a pergunta foi ret\u00f3rica ou se era pra mim mesma."}, {"bee9": "\u2014 Mano, sei l\u00e1. Quando a gente fala eu te amo."}, {"b899": "Lembrei da vez que falei que amava o Zeca. Eu n\u00e3o amava ele, mas a mar\u00e9 mansa dos relacionamentos \u00e0s vezes nos puxa para o mar aberto, deixando somente a b\u00f3ia do \"eu te amo\" pra gente se segurar. A Ana percebeu meu erro de cara."}, {"7823": "\u2014 Rafa, n\u00e3o pode ser, cara. A gente fala que ama at\u00e9 pro gar\u00e7om.\u200a\u2014\u200aNisso, a Ana segurou gentilmente no bra\u00e7o do gar\u00e7om que passava\u200a\u2014\u200aTheo, eu te amo!"}, {"2e71": "\u2014 \u00d4, dona, a gente tamb\u00e9m te ama!\u200a\u2014\u200ae saiu."}, {"edca": "Gaitamos. Eu, que n\u00e3o queria ficar pra tr\u00e1s, pedi uma dose dupla de cachacinha. A Ana me acompanhou. Tentei puxar o papo pro lado de s\u00e9ries. N\u00e3o adiantou."}, {"d1cf": "\u2014 Rafa, \u00e9 s\u00e9rio. Quando a gente ama? Tipo, quando que a gente olha no espelho e fala \"fodeu, t\u00f4 amando\"."}, {"48e0": "\u2014 Quando a gente\u2026pensa na pessoa toda hora?"}, {"18cd": "\u2014 N\u00e3o, mano, isso \u00e9 obsess\u00e3o.\u200a\u2014\u200aAna passou a m\u00e3o pelos seus cabelos curtos e cor-de-rosa levemente\u200a\u2014\u200aeu queria ficar com o filha-da-puta do Andr\u00e9 toda hora. Mas eu era ing\u00eanua e ele mandava bem. Eu n\u00e3o amava ele, eu precisava."}, {"bd3f": "\u2014 Ele transava bem?"}, {"7f2e": "\u2014 Uhum."}, {"ec91": "O Thales foi assim, pra mim, mas eu n\u00e3o quis falar pra ela que j\u00e1 tinha transado com ele. Era primo dela, ela ia rir da minha cara."}, {"d6fa": "\u2014 U\u00e9, Ana. Onde voc\u00ea quer chegar? Voc\u00ea n\u00e3o t\u00e1 gostando mais do Gusta?"}, {"a0b4": "\u2014 N\u00e3o, n\u00e3o. O Gusta \u00e9 \u00f3timo. \u00c9 legal, tem um papo cabe\u00e7a, n\u00e3o surta s\u00f3 de pensar em filhos e cozinha bem. Eu devia amar ele. E se p\u00e1 eu amo. Mas cad\u00ea a certeza?\u200a\u2014\u200aE novamente Ana cutuca o gar\u00e7om\u200a\u2014\u200aTheo, quando a gente sabe que \u00e9 amor de verdade?"}, {"338a": "O gar\u00e7om, largando mais um litr\u00e3o gelado na mesa, que abre com um estampido, responde."}, {"65ae": "\u2014 Quando traz cerveja gelada?"}, {"68c0": "Ca\u00edmos na risada novamente."}, {"5883": "\u2014 Cara, tipo, eu sei que eu amo meu trabalho. Eu amo ilustrar. Eu trabalho de casa, tem dia que eu come\u00e7o a trabalhar meia-noite e durmo at\u00e9 meio-dia. Eu tenho certeza que eu amo meu trabalho. Todo dia eu acordo e penso: \"caralho, eu faria isso at\u00e9 de gra\u00e7a se eu tivesse grana pra caralho\". Mas com relacionamento n\u00e3o. Eu nunca acordei todo dia pensando \"caralho, eu amo essa porra mais que minha vida toda!\"."}, {"712d": "Durante o papo, comecei a me incomodar. A Ana sempre foi super aberta e tranquila pra falar que n\u00e3o amava os caras que ela estava, mas eu sempre amei os meus. Ou achava que amava. Para cada um dos namoros e casos-de-mais-de-um-m\u00eas deixei escapar um eu te amo aqui e outro ali. E tinha aquela certeza de Vin\u00edcius de Moraes de que eu havia amado cada um deles. Mas, nesse momento, comecei a separ\u00e1-los em caixinhas."}, {"e250": "Car\u00eancia. Amizade. Fase da vida. Resolvi me apegar nessa teoria para defender a minha pr\u00f3pria vida."}, {"6d88": "\u2014 Ana, eu acho que amor \u00e9 uma palavra que inventaram pra agrupar um monte de sentimentos. Mesmo quando restringimos s\u00f3 para relacionamentos amorosos e sexuais, tem um monte de amor diferente. Car\u00eancia, amizade, fase da vida. Nem por isso \u00e9 menos amor. Acho que \u00e9 isso."}, {"41b5": "\u2014 Voc\u00ea explicou o tipo. Mas quando que a gente sabe?\u200a\u2014\u200aAna disse, com a cacha\u00e7a fazendo com que ela se demorasse em algumas palavras."}, {"3b2e": "Sabe quando voc\u00ea se sentiu carente e\u200a\u2014\u200ap\u00e1!\u200a\u2014\u200aligou pro Ronaldo pra dar uns beijos e depois quis dizer que amava ele? Aquilo n\u00e3o deixa de ser amor. Naquele momento era amor. Amor n\u00e3o precisa ser daqui pra sempre, pode ser daqui pra daqui \u00e0 pouco. Pode largar um \"eu te amo\" sem medo.\u200a\u2014\u200aEncerrei t\u00e3o confiante que virei o copo de cerveja, devolvendo-o com estrondo para a mesa de metal."}, {"0eaf": "Ana, b\u00eabada como estava, levantou para me aplaudir. Sem querer, ela puxou um coro de \"Parab\u00e9ns \u00e0 Voc\u00ea\" no bar. N\u00e3o era meu anivers\u00e1rio."}, {"ec7b": "\u2014 Senta, idiota!"}, {"2b04": "Depois de mais risadas e mais uma rodada de cacha\u00e7a, Ana volta a me torrar a paci\u00eancia."}, {"abab": "\u2014 Rafa, voc\u00ea \u00e9 muito decidida. Voc\u00ea tem certeza que ama o L\u00e9o. \u00c0s vezes d\u00e1 vontade de ser mais assim."}, {"5db8": "Tinha certeza? Eu nunca acordei em polvorosa por ele ter me amado ou estar comigo. Eu gostava da companhia dele e n\u00f3s combin\u00e1vamos em um monte de coisa. Era isso, e eu sempre achei que o nome disso era amor. At\u00e9 agora."}, {"4bda": "\u2014 Ana, vira essa porra e para de fazer pergunta dif\u00edcil."}, {"fe5e": "Mais uma dose. Mais uma e mais uns litr\u00f5es. Deu a hora."}, {"ae04": "Durante a volta pra casa o neg\u00f3cio bateu, a tontura chegou, o est\u00f4mago se inverteu."}, {"d2eb": "Cheguei em casa trope\u00e7ando, o L\u00e9o acordou."}, {"ed65": "\u2014 Caralho, Rafa! Duas e meia e essa barulheira."}, {"20b7": "\u2014 L\u00e9o, me azzuda aqui!\u200a\u2014\u200amal d\u00e1 tempo de chegar no banheiro. BLHAUSSSH. Tchau, tchau, cacha\u00e7a, cerveja e torresmo do bar."}, {"3b6a": "L\u00e9o segura meu cabelo. Vejo a risadinha de canto de boca do sacana."}, {"ad92": "\u2014 Para de rir, seu sacana!"}, {"cbaf": "\u2014 Tequila?"}, {"64cc": "\u2014 Teu cu!\u200a\u2014\u200aele sabia que eu odiava tequila."}, {"c6f5": "\u2014 Quer que eu fa\u00e7a um misto quente?"}, {"4cf8": "Depois de me recompor, escovar os dentes e me ajeitar na cama. L\u00e9o chega trazendo o lanche. O teto girava."}, {"0ffa": "\u2014 Amor, eu vou ficar de muita ressaca amanh\u00e3?"}, {"7ab9": "\u2014 Deixei um rem\u00e9dio e dois copos de \u00e1gua ali. Bebe um hoje e outro amanh\u00e3, com o rem\u00e9dio. Vai ficar zerada. O misto tava bom?"}, {"befd": "\u2014 Sei l\u00e1."}, {"6f77": "Ele vira e v\u00ea que consegui comer s\u00f3 metade."}, {"6ca8": "\u2014 Cuidado com as formigas nesse resto a\u00ed. Qualquer coisa grita.\u200a\u2014\u200ae virou pra dormir."}, {"ff31": "Que hom\u00e3o da porra."}, {"728f": "\u2014 L\u00e9o, eu te amo."}, {"beaa": "\u2014 Hmmmmm."}, {"30b8": "E, sim, era amor mesmo. Pelo menos at\u00e9 chegar a ressaca."}, {"622c": "Se voc\u00ea gostou, deixa um \u2764\ufe0f a\u00ed. Isso faz com que o texto alcance mais\u00a0pessoas."}, {"6dce": "Acompanhe todas as hist\u00f3rias da Revista Simbiose."}], "child": "1030_1\t1030_2\t1030_3\t1030_41030_1\t1030_2\t1030_3\t1030_41030_1\t1030_2\t1030_3\t1030_4"}